flask_ltfi_wsap/__init__.py
flask_ltfi_wsap/extension.py
flask_ltfi_wsap/models.py
flask_ltfi_wsap/utils.py
flask_ltfi_wsap/views.py
flask_ltfi_wsap-2.0.0.dist-info/licenses/LICENSE
flask_ltfi_wsap-2.0.0.dist-info/licenses/NOTICE
flask_ltfi_wsap-2.0.0.dist-info/METADATA
flask_ltfi_wsap-2.0.0.dist-info/WHEEL
flask_ltfi_wsap-2.0.0.dist-info/top_level.txt
flask_ltfi_wsap-2.0.0.dist-info/RECORD
