Metadata-Version: 2.4
Name: flask-ltfi-wsap
Version: 2.0.0
Summary: Flask extension for LTFI-WSAP (Web System Alignment Protocol) integration
Home-page: https://github.com/KiefStudioMA/LTFI-WSAP-Flask
Author: Kief Studio
Author-email: hello@ltfi.ai
License: MIT
Project-URL: Documentation, https://flask-ltfi-wsap.readthedocs.io
Project-URL: Bug Reports, https://github.com/KiefStudioMA/LTFI-WSAP-Flask/issues
Project-URL: Source, https://github.com/KiefStudioMA/LTFI-WSAP-Flask
Project-URL: Company, https://kief.studio
Project-URL: LTFI Ecosystem, https://ltfi.ai
Project-URL: WSAP Protocol, https://wsap.ltfi.ai
Keywords: flask wsap ltfi verification domain security api integration kief-studio
Classifier: Development Status :: 5 - Production/Stable
Classifier: Intended Audience :: Developers
Classifier: Topic :: Software Development :: Libraries :: Python Modules
Classifier: Topic :: Internet :: WWW/HTTP
Classifier: Topic :: Internet :: WWW/HTTP :: Dynamic Content
Classifier: Framework :: Flask
Classifier: License :: OSI Approved :: MIT License
Classifier: Programming Language :: Python :: 3
Classifier: Programming Language :: Python :: 3.8
Classifier: Programming Language :: Python :: 3.9
Classifier: Programming Language :: Python :: 3.10
Classifier: Programming Language :: Python :: 3.11
Classifier: Programming Language :: Python :: 3.12
Classifier: Operating System :: OS Independent
Requires-Python: >=3.8
License-File: LICENSE
License-File: NOTICE
Requires-Dist: Flask>=2.0.0
Requires-Dist: Werkzeug>=2.0.0
Requires-Dist: dnspython>=2.0.0
Requires-Dist: cryptography>=3.4.0
Provides-Extra: api
Requires-Dist: ltfi-wsap-sdk>=2.0.0; extra == "api"
Provides-Extra: dev
Requires-Dist: pytest>=7.0.0; extra == "dev"
Requires-Dist: pytest-flask>=1.2.0; extra == "dev"
Requires-Dist: pytest-cov>=4.0.0; extra == "dev"
Requires-Dist: black>=23.0.0; extra == "dev"
Requires-Dist: flake8>=6.0.0; extra == "dev"
Requires-Dist: mypy>=1.0.0; extra == "dev"
Dynamic: author
Dynamic: author-email
Dynamic: classifier
Dynamic: description
Dynamic: description-content-type
Dynamic: home-page
Dynamic: keywords
Dynamic: license
Dynamic: license-file
Dynamic: project-url
Dynamic: provides-extra
Dynamic: requires-dist
Dynamic: requires-python
Dynamic: summary
